postgres_ddl/Cast.py
postgres_ddl/Comment.py
postgres_ddl/Config.py
postgres_ddl/DDL.py
postgres_ddl/Database.py
postgres_ddl/Diff.py
postgres_ddl/EventTrigger.py
postgres_ddl/Extension.py
postgres_ddl/ForeignServer.py
postgres_ddl/ForeignTable.py
postgres_ddl/Function.py
postgres_ddl/Grabber.py
postgres_ddl/Grant.py
postgres_ddl/Namespace.py
postgres_ddl/Owner.py
postgres_ddl/PGQ.py
postgres_ddl/Procedure.py
postgres_ddl/Publication.py
postgres_ddl/Sequence.py
postgres_ddl/Subscription.py
postgres_ddl/System.py
postgres_ddl/TSDB_Dimension.py
postgres_ddl/TSDB_HyperTable.py
postgres_ddl/Table.py
postgres_ddl/TableColumn.py
postgres_ddl/TableConstraint.py
postgres_ddl/TableIndex.py
postgres_ddl/TablePolicy.py
postgres_ddl/TableSequence.py
postgres_ddl/TableSettings.py
postgres_ddl/TableTrigger.py
postgres_ddl/UserMapping.py
postgres_ddl/View.py
postgres_ddl/__init__.py
postgres_ddl-1.27.dist-info/LICENSE
postgres_ddl-1.27.dist-info/METADATA
postgres_ddl-1.27.dist-info/WHEEL
postgres_ddl-1.27.dist-info/top_level.txt
postgres_ddl-1.27.dist-info/RECORD
