Metadata-Version: 2.1
Name: postgres-ddl
Version: 1.27
Summary: PostgreSQL metadata grabber and comparer
Home-page: https://github.com/ish1mura/postgres_ddl
Author: ish1mura
Author-email: ek.dummy@gmail.com
Classifier: Programming Language :: Python :: 3
Classifier: License :: OSI Approved :: MIT License
Classifier: Operating System :: OS Independent
License-File: LICENSE
Requires-Dist: psycopg2-binary
